{
  "id": "c6201855c0bc2bb3",
  "name": {
    "zh": "共鸣杯"
  },
  "gameVersion": "5.2",
  "region": "CN",
  "type": "积分赛",
  "stages": [
    {
      "name": {
        "zh": "16进8"
      },
      "rules": {
        "numGames": 3,
        "mode": "conquest",
        "submitTeams": {
          "num": 3,
          "banTeams": {
            "num": 1
          }
        }
      },
      "parts": [
        {
          "name": {
            "zh": "DAY1"
          },
          "date": "2024-12-15",
          "matchIds": [
            "c6201855c0bc2bb301",
            "c6201855c0bc2bb302",
            "c6201855c0bc2bb303",
            "c6201855c0bc2bb304"
          ]
        },
        {
          "name": {
            "zh": "DAY2"
          },
          "date": "2024-12-16",
          "matchIds": [
            "c6201855c0bc2bb305",
            "c6201855c0bc2bb306",
            "c6201855c0bc2bb307",
            "c6201855c0bc2bb308"
          ]
        }
      ]
    },
    {
      "name": {
        "zh": "8进4"
      },
      "rules": {
        "numGames": 5,
        "mode": "conquest",
        "submitTeams": {
          "num": 4,
          "banTeams": {
            "num": 1
          }
        }
      },
      "parts": [
        {
          "name": {
            "zh": "DAY1"
          },
          "date": "2024-12-17",
          "matchIds": [
            "c6201855c0bc2bb309",
            "c6201855c0bc2bb310"
          ]
        },
        {
          "name": {
            "zh": "DAY2"
          },
          "date": "2024-12-18",
          "matchIds": [
            "c6201855c0bc2bb311",
            "c6201855c0bc2bb312"
          ]
        }
      ]
    }
  ]
}
